{"index.md":"BIBE15CE","practice_bind_实现一个bind.md":"Df1ZWJtU","javascript_bigfileupload_大文件上传.md":"DrG0ajOv","javascript_settimeout_如何让settimeout准时执行.md":"BwURG-vs","practice_menuarraytotree_菜单数组转树.md":"B4Jhhmwl","javascript_curry_函数柯里化.md":"CqylTZWI","readme.md":"CrhCvPB0","javascript_async2promise_async和promise的执行顺序.md":"BhylQyGO","practice_draghook_实现一个拖拽的hook.md":"Bhdvz9lC","javascript_promise_实现一个符合a_规范的promise.md":"BZc_nocM","practice_datascreenscale_大屏自适应scale方案.md":"BVnVOgQF","javascript_refreshtoken_无感刷新token.md":"DKCprZxH","example_index.md":"CHdmdTbR","javascript_promisepool_promise并发控制.md":"BllOvy6J"}
